fick1d/__init__.py
fick1d/couple.py
fick1d/cylinder.py
fick1d/slab.py
fick1d/sphere.py
fick1d/thin_film.py
fick1d-0.0.2.dist-info/LICENSE
fick1d-0.0.2.dist-info/METADATA
fick1d-0.0.2.dist-info/WHEEL
fick1d-0.0.2.dist-info/top_level.txt
fick1d-0.0.2.dist-info/RECORD
