Metadata-Version: 2.1
Name: fick1d
Version: 0.0.2
Summary: A small package for solving Fick's Second law in 1-dimension for various geometries
Home-page: https://github.com/kierannp/fick1d
Author: Kieran Nehil
Author-email: nehilkieran@gmail.com
License: UNKNOWN
Platform: UNKNOWN
Classifier: Programming Language :: Python :: 3
Classifier: License :: OSI Approved :: GNU Affero General Public License v3
Classifier: Operating System :: OS Independent
Requires-Python: >=3.6
